{
  "codice_cliente": "JC-1997-RI",
  "generatedAt": "2026-06-12T13:54:51",
  "aziende": [
    {
      "idAzienda": "az-1780557651248",
      "generatedAt": "2026-06-12T13:54:51",
      "atecoInterpretato": "",
      "deMinimisDaVerificare": true,
      "raccomandazioni": [
        {
          "id": "IT-2026-025",
          "nome": "Fondimpresa — Avviso 1/2026 Politiche Attive (formazione e assunzione)",
          "rilevanza": "alta",
          "motivazione": "Fondimpresa 100% formazione + politiche attive; fit obiettivo formazione dipendenti.",
          "motivazioneEstesa": "Copre 100% formazione dipendenti + assunzioni per aziende aderenti Fondimpresa. Ottimo fit con obiettivi Formazione dipendenti e Assunzioni/Lavoro JC. Verificare adesione. Verificare plafond de minimis residuo su RNA.",
          "scadenza": "2026-12-31",
          "importoMax": 150000,
          "tipoAgev": "Contributo a fondo perduto",
          "priorita": "Media"
        },
        {
          "id": "IT-2026-027",
          "nome": "Nuovo Piano Transizione 5.0 — Iperammortamento beni 4.0 e green (sportello GSE 2026)",
          "rilevanza": "molto_alta",
          "motivazione": "Iperammortamento beni 4.0 e FER fino 2028; ottimo per nuovo capannone + autoproduzione energia.",
          "motivazioneEstesa": "Maxi-deduzione per investimenti in beni 4.0 e autoproduzione FER. Fit eccellente con la ricostruzione del nuovo capannone JC: software, macchinari, possibili impianti FV. Cumulabile con altri incentivi.",
          "scadenza": "2028-09-30",
          "importoMax": null,
          "tipoAgev": "Agevolazione fiscale",
          "priorita": "Media"
        }
      ],
      "in_arrivo": [],
      "da_monitorare": [
        {
          "id": "IT-2026-007",
          "nome": "Voucher Cloud & Cybersecurity",
          "rilevanza": "alta",
          "motivazione": "Sospeso alta priorità: monitorare riapertura. Digitalizzazione",
          "motivazioneEstesa": "Bando sospeso ma con priorità alta. Cat: Digitalizzazione. Verificare condizioni alla riapertura per fit con investimenti JC.",
          "scadenza": "",
          "importoMax": 20000,
          "tipoAgev": "Voucher",
          "priorita": "Alta"
        },
        {
          "id": "ER-2026-003",
          "nome": "Bando internazionalizzazione ART-ER 2026",
          "rilevanza": "alta",
          "motivazione": "Sospeso alta priorità: monitorare riapertura. Internazionalizzazione",
          "motivazioneEstesa": "Bando sospeso ma con priorità alta. Cat: Internazionalizzazione. Verificare condizioni alla riapertura per fit con investimenti JC.",
          "scadenza": "",
          "importoMax": 15000,
          "tipoAgev": "Voucher",
          "priorita": "Alta"
        },
        {
          "id": "IT-2026-002",
          "nome": "Credito d'imposta Transizione 5.0",
          "rilevanza": "alta",
          "motivazione": "Sospeso alta priorità: monitorare riapertura. Digitalizzazione|Sostenibilità",
          "motivazioneEstesa": "Bando sospeso ma con priorità alta. Cat: Digitalizzazione|Sostenibilità. Verificare condizioni alla riapertura per fit con investimenti JC.",
          "scadenza": "",
          "importoMax": null,
          "tipoAgev": "Credito d'imposta",
          "priorita": "Alta"
        },
        {
          "id": "IT-2026-010",
          "nome": "Avviso Vita e Opportunita 2026",
          "rilevanza": "alta",
          "motivazione": "Sospeso alta priorità: monitorare riapertura. Altro",
          "motivazioneEstesa": "Bando sospeso con priorità alta. Cat: Altro. Verificare condizioni alla riapertura.",
          "scadenza": "2026-08-29",
          "importoMax": 3000000,
          "tipoAgev": "Contributo a fondo perduto",
          "priorita": "Alta"
        },
        {
          "id": "IT-2026-016",
          "nome": "Iperammortamento 2026-2028 — Maxi-deduzione beni strumentali 4.0",
          "rilevanza": "alta",
          "motivazione": "Sospeso alta priorità: monitorare riapertura. Digitalizzazione",
          "motivazioneEstesa": "Bando sospeso con priorità alta. Cat: Digitalizzazione. Verificare condizioni alla riapertura.",
          "scadenza": "2028-09-30",
          "importoMax": null,
          "tipoAgev": "Agevolazione fiscale",
          "priorita": "Alta"
        }
      ],
      "esclusi_per_ateco": [
        {
          "id": "EU-2026-001",
          "nome": "EIC Accelerator — Fase Open",
          "ateco_bando": "tutti (deep tech)",
          "motivo": "JC è concessionaria auto, non deep tech"
        },
        {
          "id": "EU-2026-002",
          "nome": "LIFE Programme 2026 — Standard Action Projects (Environment & Climate)",
          "ateco_bando": "tutti",
          "motivo": "Progetti ambiente/clima a forte componente R&S; non in linea con commercio auto"
        },
        {
          "id": "IT-2026-004",
          "nome": "Voucher 3I — Brevetti+ (Investire in Innovazione)",
          "ateco_bando": "tutti (innovazione brevettabile)",
          "motivo": "Per brevetti su invenzioni; JC è concessionaria"
        },
        {
          "id": "EU-2026-004",
          "nome": "EIC Transition 2026",
          "ateco_bando": "tutti (deep tech)",
          "motivo": "Richiede risultati EIC/Horizon precedenti; JC concessionaria"
        },
        {
          "id": "ER-2025-002",
          "nome": "FESR ER — STEP 2025: investimenti produttivi e R&S in tecnologie strategiche",
          "ateco_bando": "tutti (focus tech strategiche)",
          "motivo": "Tecnologie strategiche deep tech/clean tech; JC è commercio/officina auto"
        },
        {
          "id": "IT-2026-012",
          "nome": "Smart&Start Italia — Sostegno startup innovative ad alto contenuto tecnologico",
          "ateco_bando": "tutti (solo startup innovative)",
          "motivo": "Riservato startup innovative; JC esiste dal 1997"
        },
        {
          "id": "IT-2026-019",
          "nome": "Premio per lo Sviluppo Sostenibile 2026 — 16a Edizione",
          "ateco_bando": "settori eco-innovazione",
          "motivo": "Per imprese eco-innovative; JC è concessionaria tradizionale"
        },
        {
          "id": "IT-2026-022",
          "nome": "Autoimpiego Centro-Nord — Invitalia (under 35)",
          "ateco_bando": "tutti eccetto agricoltura",
          "motivo": "Per nuove imprese under 35; JC esiste dal 1997"
        },
        {
          "id": "IT-2026-023",
          "nome": "SIMEST — Misura Stati Uniti (internazionalizzazione USA)",
          "ateco_bando": "tutti",
          "motivo": "Internazionalizzazione USA; JC opera solo in Provincia Rimini"
        },
        {
          "id": "ER-2026-015",
          "nome": "FESR ER — Sostegno innovazione commercio vicinato, pubblici esercizi e attività polifunzionali 2026",
          "ateco_bando": "47, 56",
          "motivo": "ATECO 47/56 (commercio dettaglio non specializzato/somministrazione); JC è ATECO 45 (auto)"
        },
        {
          "id": "IT-2026-026",
          "nome": "SIMEST — Misura Energia per la Competitività Internazionale 2026",
          "ateco_bando": "tutti escluse non esportatrici",
          "motivo": "Per imprese esportatrici; JC opera solo in Provincia Rimini"
        },
        {
          "id": "ER-2026-016",
          "nome": "FESR ER — Bando integrativo PRECISEU: innovazione deep tech nel settore salute",
          "ateco_bando": "tutti (focus salute/deep tech)",
          "motivo": "Focus salute/medicina precisione; JC è concessionaria"
        },
        {
          "id": "ER-2026-018",
          "nome": "CSR ER — SRD03 Trasformazione prodotti agricoli (diversificazione aziende agricole)",
          "ateco_bando": "A01",
          "motivo": "ATECO A01 (agricoltura); JC è commercio auto"
        }
      ]
    }
  ]
}